ottobox/__init__.py
ottobox/_frontend.py
ottobox/_version.py
ottobox/example.py
ottobox/labextension/package.json
ottobox/labextension/static/480.2cccbb8e7c4ba2c17b79.js
ottobox/labextension/static/568.767cd4e735ef90b16ea4.js
ottobox/labextension/static/remoteEntry.72b0034ef4ec743ea852.js
ottobox/labextension/static/style.js
ottobox/labextension/static/third-party-licenses.json
ottobox/nbextension/extension.js
ottobox/nbextension/index.js
ottobox/nbextension/index.js.map
ottobox/tests/__init__.py
ottobox/tests/conftest.py
ottobox/tests/test_example.py
ottobox/tests/test_nbextension_path.py
ottobox-0.1.0.data/data/etc/jupyter/nbconfig/notebook.d/ottobox.json
ottobox-0.1.0.data/data/share/jupyter/labextensions/ottobox/install.json
ottobox-0.1.0.data/data/share/jupyter/labextensions/ottobox/package.json
ottobox-0.1.0.data/data/share/jupyter/labextensions/ottobox/static/480.2cccbb8e7c4ba2c17b79.js
ottobox-0.1.0.data/data/share/jupyter/labextensions/ottobox/static/568.767cd4e735ef90b16ea4.js
ottobox-0.1.0.data/data/share/jupyter/labextensions/ottobox/static/remoteEntry.72b0034ef4ec743ea852.js
ottobox-0.1.0.data/data/share/jupyter/labextensions/ottobox/static/style.js
ottobox-0.1.0.data/data/share/jupyter/labextensions/ottobox/static/third-party-licenses.json
ottobox-0.1.0.data/data/share/jupyter/nbextensions/ottobox/extension.js
ottobox-0.1.0.data/data/share/jupyter/nbextensions/ottobox/index.js
ottobox-0.1.0.data/data/share/jupyter/nbextensions/ottobox/index.js.map
ottobox-0.1.0.dist-info/LICENSE.txt
ottobox-0.1.0.dist-info/METADATA
ottobox-0.1.0.dist-info/WHEEL
ottobox-0.1.0.dist-info/top_level.txt
ottobox-0.1.0.dist-info/RECORD
